sphinx_examples/__init__.py
sphinx_examples/_static/styles/sphinx-examples.css
sphinx_examples-0.0.5.dist-info/LICENSE
sphinx_examples-0.0.5.dist-info/WHEEL
sphinx_examples-0.0.5.dist-info/METADATA
sphinx_examples-0.0.5.dist-info/RECORD
