Metadata-Version: 2.1
Name: sphinx-examples
Version: 0.0.5
Summary: A lightweight example directive to make it easy to demonstrate code / results.
Keywords: documentation,sphinx
Author-email: Executable Book Project <executablebooks@gmail.com>
Requires-Python: >=3.7
Classifier: Development Status :: 4 - Beta
Classifier: License :: OSI Approved :: BSD License
Classifier: Programming Language :: Python :: 3
Classifier: Programming Language :: Python :: 3 :: Only
Classifier: Programming Language :: Python :: 3.7
Classifier: Programming Language :: Python :: 3.8
Classifier: Programming Language :: Python :: 3.9
Classifier: Programming Language :: Python :: 3.10
Classifier: Programming Language :: Python :: Implementation :: CPython
Classifier: Topic :: Software Development :: Libraries :: Python Modules
Classifier: Topic :: Text Processing :: Markup
Requires-Dist: sphinx>4
Requires-Dist: sphinx-design
Requires-Dist: sphinx-book-theme ; extra == "sphinx"
Requires-Dist: sphinx-copybutton ; extra == "sphinx"
Requires-Dist: myst-parser ; extra == "sphinx"
Requires-Dist: sphinx-rtd-theme ; extra == "sphinx"
Requires-Dist: furo ; extra == "sphinx"
Project-URL: Documentation, https://executablebooks.org/
Project-URL: Funding, https://executablebooks.org
Project-URL: Homepage, https://executablebooks.org/
Project-URL: Source, https://github.com/executablebooks/sphinx-examples/
Project-URL: Tracker, https://github.com/executablebooks/sphinx-examples/issues
Provides-Extra: sphinx
